MANIFEST.in
README.rst
pyproject.toml
setup.cfg
setup.py
./eleve/cython_storage.cpp
eleve/__init__.py
eleve/cython_storage.cpp
eleve/cython_storage.pyx
eleve/memory.py
eleve/segment.py
eleve.egg-info/PKG-INFO
eleve.egg-info/SOURCES.txt
eleve.egg-info/dependency_links.txt
eleve.egg-info/top_level.txt
eleve/preprocessing/__init__.py
eleve/preprocessing/chinese.py
scripts/eleve-chinese
scripts/eleve-train