Metadata-Version: 1.1
Name: eleve
Version: 20.10.8
Summary: Extraction de LExique par Variation d'Entropie - Lexicon extraction based on the variation of entropy
Home-page: https://github.com/kodexlab/eleve
Author: Pierre Magistry, Korantin Auguste, Emmanuel Navarro
Author-email: contact@kodexlab.com
License: UNKNOWN
Platform: UNKNOWN
Classifier: Programming Language :: Python
Classifier: Development Status :: 5 - Production/Stable
Classifier: License :: OSI Approved :: GNU Library or Lesser General Public License (LGPL)
Classifier: Natural Language :: French
Classifier: Operating System :: OS Independent
Classifier: Programming Language :: Python :: 3.5
Classifier: Programming Language :: Python :: 3.6
Classifier: Programming Language :: Python :: 3.7
Classifier: Programming Language :: Cython
Classifier: Topic :: Scientific/Engineering
